CindyScriptPygments.py
CindyScriptPygments-0.2.0.dist-info/DESCRIPTION.rst
CindyScriptPygments-0.2.0.dist-info/METADATA
CindyScriptPygments-0.2.0.dist-info/RECORD
CindyScriptPygments-0.2.0.dist-info/WHEEL
CindyScriptPygments-0.2.0.dist-info/entry_points.txt
CindyScriptPygments-0.2.0.dist-info/metadata.json
CindyScriptPygments-0.2.0.dist-info/top_level.txt
CindyScriptPygments-0.2.0.dist-info/zip-safe
