Metadata-Version: 2.0
Name: CindyScriptPygments
Version: 0.2.0
Summary: Pygments plugin for CindyScript
Home-page: https://github.com/CindyJS/CindyScriptPygments
Author: Martin von Gagern
Author-email: gagern@ma.tum.de
License: Dual license BSD 2-clause or Apache 2
Download-URL: https://pypi.python.org/pypi/CindyScriptPygments#downloads
Platform: UNKNOWN
Classifier: Development Status :: 3 - Alpha
Classifier: Environment :: Plugins
Classifier: Intended Audience :: Developers
Classifier: License :: OSI Approved :: BSD License
Classifier: License :: OSI Approved :: Apache Software License
Classifier: Operating System :: OS Independent
Classifier: Programming Language :: Python
Classifier: Programming Language :: Python :: 2
Classifier: Programming Language :: Python :: 3
Classifier: Topic :: Documentation
Classifier: Topic :: Internet :: WWW/HTTP
Classifier: Topic :: Scientific/Engineering :: Mathematics
Classifier: Topic :: Text Processing :: Filters
Requires-Dist: Pygments
